S3StorageCostEstimator.py
s3_cost_estimator-3.0.0.dist-info/licenses/LICENCE
s3_cost_estimator-3.0.0.dist-info/METADATA
s3_cost_estimator-3.0.0.dist-info/WHEEL
s3_cost_estimator-3.0.0.dist-info/top_level.txt
s3_cost_estimator-3.0.0.dist-info/RECORD
