Metadata-Version: 2.4
Name: s3-cost-estimator
Version: 3.0.0
Summary: A Python library to estimate AWS S3 storage costs using Cost Explorer
Author:  Sai Niranjan Chitturi, Leela Sai Surya Veer Pedarla, OpenAI, xAI.
Project-URL: Homepage, https://github.com/SaiNiranjanChitturi/s3-cost-estimator
Requires-Python: >=3.8
License-File: LICENCE
Requires-Dist: boto3>=1.20.0
Dynamic: license-file
